tiramisu/__init__.py
tiramisu/schemas.py
tiramisu/agents/__init__.py
tiramisu/agents/digital_expert.py
tiramisu/agents/strategy_expert.py
tiramisu/agents/supervisor.py
tiramisu/agents/tech_expert.py
tiramisu/api/__init__.py
tiramisu/api/conversation_routes.py
tiramisu/api/langchain_routes.py
tiramisu/api/main.py
tiramisu/cli/__init__.py
tiramisu/cli/commands.py
tiramisu/config/__init__.py
tiramisu/config/settings.py
tiramisu/core/__init__.py
tiramisu/core/conversation_db.py
tiramisu/core/conversation_manager.py
tiramisu/core/indexer.py
tiramisu/core/orchestrator.py
tiramisu/core/tiramisu_rag.py
tiramisu/governance/__init__.py
tiramisu/governance/orchestrator.py
tiramisu/memory/__init__.py
tiramisu/memory/redis_manager.py
tiramisu/memory/session_memory.py
tiramisu/personas/__init__.py
tiramisu/personas/base.py
tiramisu/personas/persona_g.py
tiramisu/personas/persona_k.py
tiramisu/personas/persona_m.py
tiramisu/rao/__init__.py
tiramisu/rao/rao_4_validator.py
tiramisu/rao/rao_5_analyzer.py
tiramisu/rao/rao_6_planner.py
tiramisu/router/__init__.py
tiramisu/utils/__init__.py
tiramisu/validation/__init__.py
tiramisu/validation/auditor.py
tiramisu/validation/fact_checker.py
tiramisu_framework-3.0.0.dist-info/licenses/LICENSE
tiramisu_framework-3.0.0.dist-info/METADATA
tiramisu_framework-3.0.0.dist-info/WHEEL
tiramisu_framework-3.0.0.dist-info/entry_points.txt
tiramisu_framework-3.0.0.dist-info/top_level.txt
tiramisu_framework-3.0.0.dist-info/RECORD
